{"error":0,"nodos":[{"latitud":-26.8685580000000000,"longitud":-65.2421630000000000,"parada":false,"codigoParada":"","descripcionParada":""},{"latitud":-26.8685660000000000,"longitud":-65.2421730000000000,"parada":false,"codigoParada":"","descripcionParada":""},{"latitud":-26.8685650000000000,"longitud":-65.2421780000000000,"parada":false,"codigoParada":"","descripcionParada":""},{"latitud":-26.8685590000000000,"longitud":-65.2421820000000000,"parada":false,"codigoParada":"","descripcionParada":""},{"latitud":-26.8685550000000000,"longitud":-65.2421820000000000,"parada":false,"codigoParada":"","descripcionParada":""},{"latitud":-26.8685560000000000,"longitud":-65.2421830000000000,"parada":false,"codigoParada":"","descripcionParada":""},{"latitud":-26.8685600000000000,"longitud":-65.2421860000000000,"parada":false,"codigoParada":"","descripcionParada":""},{"latitud":-26.8684780000000000,"longitud":-65.2423920000000000,"parada":false,"codigoParada":"","descripcionParada":""},{"latitud":-26.8680800000000000,"longitud":-65.2443230000000000,"parada":false,"codigoParada":"","descripcionParada":""},{"latitud":-26.8677760000000000,"longitud":-65.2459790000000000,"parada":false,"codigoParada":"","descripcionParada":""},{"latitud":-26.8670260000000000,"longitud":-65.2499270000000000,"parada":false,"codigoParada":"","descripcionParada":""},{"latitud":-26.8666480000000000,"longitud":-65.2519100000000000,"parada":false,"codigoParada":"","descripcionParada":""},{"latitud":-26.8662630000000000,"longitud":-65.2538860000000000,"parada":false,"codigoParada":"","descripcionParada":""},{"latitud":-26.8660580000000000,"longitud":-65.2543920000000000,"parada":false,"codigoParada":"","descripcionParada":""},{"latitud":-26.8659090000000000,"longitud":-65.2543550000000000,"parada":false,"codigoParada":"","descripcionParada":""},{"latitud":-26.8641060000000000,"longitud":-65.2539290000000000,"parada":false,"codigoParada":"","descripcionParada":""},{"latitud":-26.8636110000000000,"longitud":-65.2536900000000000,"parada":false,"codigoParada":"","descripcionParada":""},{"latitud":-26.8636350000000000,"longitud":-65.2535800000000000,"parada":false,"codigoParada":"","descripcionParada":""},{"latitud":-26.8640070000000000,"longitud":-65.2515620000000000,"parada":false,"codigoParada":"","descripcionParada":""},{"latitud":-26.8643820000000000,"longitud":-65.2495600000000000,"parada":false,"codigoParada":"","descripcionParada":""},{"latitud":-26.8647450000000000,"longitud":-65.2475390000000000,"parada":false,"codigoParada":"","descripcionParada":""},{"latitud":-26.8651190000000000,"longitud":-65.2455730000000000,"parada":false,"codigoParada":"","descripcionParada":""},{"latitud":-26.8654740000000000,"longitud":-65.2435070000000000,"parada":false,"codigoParada":"","descripcionParada":""},{"latitud":-26.8654900000000000,"longitud":-65.2428350000000000,"parada":false,"codigoParada":"","descripcionParada":""},{"latitud":-26.8653440000000000,"longitud":-65.2427750000000000,"parada":false,"codigoParada":"","descripcionParada":""},{"latitud":-26.8636010000000000,"longitud":-65.2423330000000000,"parada":false,"codigoParada":"","descripcionParada":""},{"latitud":-26.8627670000000000,"longitud":-65.2418310000000000,"parada":false,"codigoParada":"","descripcionParada":""},{"latitud":-26.8631530000000000,"longitud":-65.2404690000000000,"parada":false,"codigoParada":"","descripcionParada":""},{"latitud":-26.8642730000000000,"longitud":-65.2405000000000000,"parada":false,"codigoParada":"","descripcionParada":""},{"latitud":-26.8646270000000000,"longitud":-65.2385510000000000,"parada":false,"codigoParada":"","descripcionParada":""},{"latitud":-26.8650030000000000,"longitud":-65.2365490000000000,"parada":false,"codigoParada":"","descripcionParada":""},{"latitud":-26.8656280000000000,"longitud":-65.2347170000000000,"parada":false,"codigoParada":"","descripcionParada":""},{"latitud":-26.8659600000000000,"longitud":-65.2344350000000000,"parada":false,"codigoParada":"","descripcionParada":""},{"latitud":-26.8660170000000000,"longitud":-65.2344870000000000,"parada":false,"codigoParada":"","descripcionParada":""},{"latitud":-26.8675510000000000,"longitud":-65.2355530000000000,"parada":false,"codigoParada":"","descripcionParada":""},{"latitud":-26.8690650000000000,"longitud":-65.2366270000000000,"parada":false,"codigoParada":"","descripcionParada":""},{"latitud":-26.8720790000000000,"longitud":-65.2390640000000000,"parada":false,"codigoParada":"","descripcionParada":""},{"latitud":-26.8728020000000000,"longitud":-65.2396380000000000,"parada":false,"codigoParada":"","descripcionParada":""},{"latitud":-26.8728780000000000,"longitud":-65.2394600000000000,"parada":false,"codigoParada":"","descripcionParada":""},{"latitud":-26.8732640000000000,"longitud":-65.2375060000000000,"parada":false,"codigoParada":"","descripcionParada":""},{"latitud":-26.8736620000000000,"longitud":-65.2355320000000000,"parada":false,"codigoParada":"","descripcionParada":""},{"latitud":-26.8740860000000000,"longitud":-65.2335640000000000,"parada":false,"codigoParada":"","descripcionParada":""},{"latitud":-26.8744770000000000,"longitud":-65.2315950000000000,"parada":false,"codigoParada":"","descripcionParada":""},{"latitud":-26.8748440000000000,"longitud":-65.2295740000000000,"parada":false,"codigoParada":"","descripcionParada":""},{"latitud":-26.8752650000000000,"longitud":-65.2275660000000000,"parada":false,"codigoParada":"","descripcionParada":""},{"latitud":-26.8756570000000000,"longitud":-65.2255520000000000,"parada":false,"codigoParada":"","descripcionParada":""},{"latitud":-26.8757840000000000,"longitud":-65.2241880000000000,"parada":false,"codigoParada":"","descripcionParada":""},{"latitud":-26.8741820000000000,"longitud":-65.2234520000000000,"parada":false,"codigoParada":"","descripcionParada":""},{"latitud":-26.8725120000000000,"longitud":-65.2226940000000000,"parada":false,"codigoParada":"","descripcionParada":""},{"latitud":-26.8719000000000000,"longitud":-65.2224390000000000,"parada":false,"codigoParada":"","descripcionParada":""},{"latitud":-26.8708190000000000,"longitud":-65.2219530000000000,"parada":false,"codigoParada":"","descripcionParada":""},{"latitud":-26.8703340000000000,"longitud":-65.2218100000000000,"parada":false,"codigoParada":"","descripcionParada":""},{"latitud":-26.8690480000000000,"longitud":-65.2215590000000000,"parada":false,"codigoParada":"","descripcionParada":""},{"latitud":-26.8672660000000000,"longitud":-65.2212150000000000,"parada":false,"codigoParada":"","descripcionParada":""},{"latitud":-26.8673620000000000,"longitud":-65.2212340000000000,"parada":false,"codigoParada":"","descripcionParada":""},{"latitud":-26.8666890000000000,"longitud":-65.2211130000000000,"parada":false,"codigoParada":"","descripcionParada":""},{"latitud":-26.8649800000000000,"longitud":-65.2206760000000000,"parada":false,"codigoParada":"","descripcionParada":""},{"latitud":-26.8643650000000000,"longitud":-65.2204720000000000,"parada":false,"codigoParada":"","descripcionParada":""},{"latitud":-26.8631870000000000,"longitud":-65.2200840000000000,"parada":false,"codigoParada":"","descripcionParada":""},{"latitud":-26.8628370000000000,"longitud":-65.2199690000000000,"parada":false,"codigoParada":"","descripcionParada":""},{"latitud":-26.8614060000000000,"longitud":-65.2194820000000000,"parada":false,"codigoParada":"","descripcionParada":""},{"latitud":-26.8612580000000000,"longitud":-65.2194330000000000,"parada":false,"codigoParada":"","descripcionParada":""},{"latitud":-26.8600630000000000,"longitud":-65.2190370000000000,"parada":false,"codigoParada":"","descripcionParada":""},{"latitud":-26.8585090000000000,"longitud":-65.2185050000000000,"parada":false,"codigoParada":"","descripcionParada":""},{"latitud":-26.8583110000000000,"longitud":-65.2184420000000000,"parada":false,"codigoParada":"","descripcionParada":""},{"latitud":-26.8565530000000000,"longitud":-65.2177960000000000,"parada":false,"codigoParada":"","descripcionParada":""},{"latitud":-26.8561250000000000,"longitud":-65.2176470000000000,"parada":false,"codigoParada":"","descripcionParada":""},{"latitud":-26.8547800000000000,"longitud":-65.2172070000000000,"parada":false,"codigoParada":"","descripcionParada":""},{"latitud":-26.8547160000000000,"longitud":-65.2171850000000000,"parada":false,"codigoParada":"","descripcionParada":""},{"latitud":-26.8530390000000000,"longitud":-65.2166310000000000,"parada":false,"codigoParada":"","descripcionParada":""},{"latitud":-26.8522330000000000,"longitud":-65.2163650000000000,"parada":false,"codigoParada":"","descripcionParada":""},{"latitud":-26.8513070000000000,"longitud":-65.2160560000000000,"parada":false,"codigoParada":"","descripcionParada":""},{"latitud":-26.8507930000000000,"longitud":-65.2158900000000000,"parada":false,"codigoParada":"","descripcionParada":""},{"latitud":-26.8502410000000000,"longitud":-65.2155250000000000,"parada":false,"codigoParada":"","descripcionParada":""},{"latitud":-26.8503860000000000,"longitud":-65.2150290000000000,"parada":false,"codigoParada":"","descripcionParada":""},{"latitud":-26.8504800000000000,"longitud":-65.2142130000000000,"parada":false,"codigoParada":"","descripcionParada":""},{"latitud":-26.8503770000000000,"longitud":-65.2141840000000000,"parada":false,"codigoParada":"","descripcionParada":""},{"latitud":-26.8485980000000000,"longitud":-65.2137380000000000,"parada":false,"codigoParada":"","descripcionParada":""},{"latitud":-26.8485980000000000,"longitud":-65.2137380000000000,"parada":false,"codigoParada":"","descripcionParada":""},{"latitud":-26.8468340000000000,"longitud":-65.2133030000000000,"parada":false,"codigoParada":"","descripcionParada":""},{"latitud":-26.8450570000000000,"longitud":-65.2128930000000000,"parada":false,"codigoParada":"","descripcionParada":""},{"latitud":-26.8445900000000000,"longitud":-65.2127770000000000,"parada":false,"codigoParada":"","descripcionParada":""},{"latitud":-26.8432640000000000,"longitud":-65.2124320000000000,"parada":false,"codigoParada":"","descripcionParada":""},{"latitud":-26.8416230000000000,"longitud":-65.2121220000000000,"parada":false,"codigoParada":"","descripcionParada":""},{"latitud":-26.8412180000000000,"longitud":-65.2120080000000000,"parada":false,"codigoParada":"","descripcionParada":""},{"latitud":-26.8398650000000000,"longitud":-65.2116400000000000,"parada":false,"codigoParada":"","descripcionParada":""},{"latitud":-26.8391420000000000,"longitud":-65.2114570000000000,"parada":false,"codigoParada":"","descripcionParada":""},{"latitud":-26.8384220000000000,"longitud":-65.2112810000000000,"parada":false,"codigoParada":"","descripcionParada":""},{"latitud":-26.8370100000000000,"longitud":-65.2109780000000000,"parada":false,"codigoParada":"","descripcionParada":""},{"latitud":-26.8352130000000000,"longitud":-65.2105190000000000,"parada":false,"codigoParada":"","descripcionParada":""},{"latitud":-26.8351570000000000,"longitud":-65.2104950000000000,"parada":false,"codigoParada":"","descripcionParada":""},{"latitud":-26.8338180000000000,"longitud":-65.2103390000000000,"parada":false,"codigoParada":"","descripcionParada":""},{"latitud":-26.8328610000000000,"longitud":-65.2099510000000000,"parada":false,"codigoParada":"","descripcionParada":""},{"latitud":-26.8329020000000000,"longitud":-65.2098400000000000,"parada":false,"codigoParada":"","descripcionParada":""},{"latitud":-26.8330000000000000,"longitud":-65.2088270000000000,"parada":false,"codigoParada":"","descripcionParada":""},{"latitud":-26.8329750000000000,"longitud":-65.2085770000000000,"parada":false,"codigoParada":"","descripcionParada":""},{"latitud":-26.8333510000000000,"longitud":-65.2066730000000000,"parada":false,"codigoParada":"","descripcionParada":""},{"latitud":-26.8336980000000000,"longitud":-65.2046710000000000,"parada":false,"codigoParada":"","descripcionParada":""},{"latitud":-26.8342330000000000,"longitud":-65.2028230000000000,"parada":false,"codigoParada":"","descripcionParada":""},{"latitud":-26.8342940000000000,"longitud":-65.2025540000000000,"parada":false,"codigoParada":"","descripcionParada":""},{"latitud":-26.8347250000000000,"longitud":-65.2005990000000000,"parada":false,"codigoParada":"","descripcionParada":""},{"latitud":-26.8351930000000000,"longitud":-65.1986430000000000,"parada":false,"codigoParada":"","descripcionParada":""},{"latitud":-26.8353400000000000,"longitud":-65.1977580000000000,"parada":false,"codigoParada":"","descripcionParada":""},{"latitud":-26.8352300000000000,"longitud":-65.1977320000000000,"parada":false,"codigoParada":"","descripcionParada":""},{"latitud":-26.8346970000000000,"longitud":-65.1976090000000000,"parada":false,"codigoParada":"","descripcionParada":""},{"latitud":-26.8335230000000000,"longitud":-65.1973140000000000,"parada":false,"codigoParada":"","descripcionParada":""},{"latitud":-26.8328750000000000,"longitud":-65.1971270000000000,"parada":false,"codigoParada":"","descripcionParada":""},{"latitud":-26.8311330000000000,"longitud":-65.1967100000000000,"parada":false,"codigoParada":"","descripcionParada":""},{"latitud":-26.8312230000000000,"longitud":-65.1967280000000000,"parada":false,"codigoParada":"","descripcionParada":""},{"latitud":-26.8292730000000000,"longitud":-65.1962800000000000,"parada":false,"codigoParada":"","descripcionParada":""},{"latitud":-26.8277700000000000,"longitud":-65.1958960000000000,"parada":false,"codigoParada":"","descripcionParada":""},{"latitud":-26.8274990000000000,"longitud":-65.1958260000000000,"parada":false,"codigoParada":"","descripcionParada":""},{"latitud":-26.8268820000000000,"longitud":-65.1955660000000000,"parada":false,"codigoParada":"","descripcionParada":""},{"latitud":-26.8269150000000000,"longitud":-65.1954480000000000,"parada":false,"codigoParada":"","descripcionParada":""},{"latitud":-26.8270890000000000,"longitud":-65.1946360000000000,"parada":false,"codigoParada":"","descripcionParada":""},{"latitud":-26.8271710000000000,"longitud":-65.1936610000000000,"parada":false,"codigoParada":"","descripcionParada":""},{"latitud":-26.8271950000000000,"longitud":-65.1934280000000000,"parada":false,"codigoParada":"","descripcionParada":""},{"latitud":-26.8270910000000000,"longitud":-65.1931250000000000,"parada":false,"codigoParada":"","descripcionParada":""},{"latitud":-26.8269590000000000,"longitud":-65.1931150000000000,"parada":false,"codigoParada":"","descripcionParada":""},{"latitud":-26.8262610000000000,"longitud":-65.1929880000000000,"parada":false,"codigoParada":"","descripcionParada":""},{"latitud":-26.8258540000000000,"longitud":-65.1930050000000000,"parada":false,"codigoParada":"","descripcionParada":""},{"latitud":-26.8258430000000000,"longitud":-65.1931330000000000,"parada":false,"codigoParada":"","descripcionParada":""},{"latitud":-26.8256450000000000,"longitud":-65.1944920000000000,"parada":false,"codigoParada":"","descripcionParada":""},{"latitud":-26.8255550000000000,"longitud":-65.1950620000000000,"parada":false,"codigoParada":"","descripcionParada":""},{"latitud":-26.8253290000000000,"longitud":-65.1968910000000000,"parada":false,"codigoParada":"","descripcionParada":""},{"latitud":-26.8250390000000000,"longitud":-65.1989320000000000,"parada":false,"codigoParada":"","descripcionParada":""},{"latitud":-26.8250330000000000,"longitud":-65.1990310000000000,"parada":false,"codigoParada":"","descripcionParada":""},{"latitud":-26.8247130000000000,"longitud":-65.2009410000000000,"parada":false,"codigoParada":"","descripcionParada":""},{"latitud":-26.8244640000000000,"longitud":-65.2020630000000000,"parada":false,"codigoParada":"","descripcionParada":""},{"latitud":-26.8242470000000000,"longitud":-65.2028840000000000,"parada":false,"codigoParada":"","descripcionParada":""},{"latitud":-26.8242030000000000,"longitud":-65.2030690000000000,"parada":false,"codigoParada":"","descripcionParada":""},{"latitud":-26.8237510000000000,"longitud":-65.2050030000000000,"parada":false,"codigoParada":"","descripcionParada":""},{"latitud":-26.8237160000000000,"longitud":-65.2052470000000000,"parada":false,"codigoParada":"","descripcionParada":""},{"latitud":-26.8234040000000000,"longitud":-65.2070030000000000,"parada":false,"codigoParada":"","descripcionParada":""},{"latitud":-26.8231420000000000,"longitud":-65.2082310000000000,"parada":false,"codigoParada":"","descripcionParada":""},{"latitud":-26.8230290000000000,"longitud":-65.2088860000000000,"parada":false,"codigoParada":"","descripcionParada":""},{"latitud":-26.8230370000000000,"longitud":-65.2090970000000000,"parada":false,"codigoParada":"","descripcionParada":""},{"latitud":-26.8231290000000000,"longitud":-65.2091540000000000,"parada":false,"codigoParada":"","descripcionParada":""},{"latitud":-26.8242960000000000,"longitud":-65.2094930000000000,"parada":false,"codigoParada":"","descripcionParada":""},{"latitud":-26.8261110000000000,"longitud":-65.2100180000000000,"parada":false,"codigoParada":"","descripcionParada":""},{"latitud":-26.8278840000000000,"longitud":-65.2104860000000000,"parada":false,"codigoParada":"","descripcionParada":""},{"latitud":-26.8296770000000000,"longitud":-65.2109310000000000,"parada":false,"codigoParada":"","descripcionParada":""},{"latitud":-26.8314260000000000,"longitud":-65.2113770000000000,"parada":false,"codigoParada":"","descripcionParada":""},{"latitud":-26.8322460000000000,"longitud":-65.2115300000000000,"parada":false,"codigoParada":"","descripcionParada":""},{"latitud":-26.8339880000000000,"longitud":-65.2120050000000000,"parada":false,"codigoParada":"","descripcionParada":""},{"latitud":-26.8357440000000000,"longitud":-65.2124610000000000,"parada":false,"codigoParada":"","descripcionParada":""},{"latitud":-26.8374550000000000,"longitud":-65.2128740000000000,"parada":false,"codigoParada":"","descripcionParada":""},{"latitud":-26.8377050000000000,"longitud":-65.2129450000000000,"parada":false,"codigoParada":"","descripcionParada":""},{"latitud":-26.8394500000000000,"longitud":-65.2134310000000000,"parada":false,"codigoParada":"","descripcionParada":""},{"latitud":-26.8412410000000000,"longitud":-65.2138200000000000,"parada":false,"codigoParada":"","descripcionParada":""},{"latitud":-26.8417750000000000,"longitud":-65.2139750000000000,"parada":false,"codigoParada":"","descripcionParada":""},{"latitud":-26.8419730000000000,"longitud":-65.2139030000000000,"parada":false,"codigoParada":"","descripcionParada":""},{"latitud":-26.8422740000000000,"longitud":-65.2138180000000000,"parada":false,"codigoParada":"","descripcionParada":""},{"latitud":-26.8440630000000000,"longitud":-65.2142580000000000,"parada":false,"codigoParada":"","descripcionParada":""},{"latitud":-26.8458700000000000,"longitud":-65.2147240000000000,"parada":false,"codigoParada":"","descripcionParada":""},{"latitud":-26.8476780000000000,"longitud":-65.2151770000000000,"parada":false,"codigoParada":"","descripcionParada":""},{"latitud":-26.8494990000000000,"longitud":-65.2156300000000000,"parada":false,"codigoParada":"","descripcionParada":""},{"latitud":-26.8512380000000000,"longitud":-65.2161690000000000,"parada":false,"codigoParada":"","descripcionParada":""},{"latitud":-26.8530350000000000,"longitud":-65.2167300000000000,"parada":false,"codigoParada":"","descripcionParada":""},{"latitud":-26.8548350000000000,"longitud":-65.2173130000000000,"parada":false,"codigoParada":"","descripcionParada":""},{"latitud":-26.8565740000000000,"longitud":-65.2179130000000000,"parada":false,"codigoParada":"","descripcionParada":""},{"latitud":-26.8582970000000000,"longitud":-65.2185760000000000,"parada":false,"codigoParada":"","descripcionParada":""},{"latitud":-26.8600620000000000,"longitud":-65.2191630000000000,"parada":false,"codigoParada":"","descripcionParada":""},{"latitud":-26.8618650000000000,"longitud":-65.2197570000000000,"parada":false,"codigoParada":"","descripcionParada":""},{"latitud":-26.8635990000000000,"longitud":-65.2203290000000000,"parada":false,"codigoParada":"","descripcionParada":""},{"latitud":-26.8653580000000000,"longitud":-65.2209030000000000,"parada":false,"codigoParada":"","descripcionParada":""},{"latitud":-26.8671880000000000,"longitud":-65.2213020000000000,"parada":false,"codigoParada":"","descripcionParada":""},{"latitud":-26.8690250000000000,"longitud":-65.2216230000000000,"parada":false,"codigoParada":"","descripcionParada":""},{"latitud":-26.8707860000000000,"longitud":-65.2220390000000000,"parada":false,"codigoParada":"","descripcionParada":""},{"latitud":-26.8725020000000000,"longitud":-65.2227830000000000,"parada":false,"codigoParada":"","descripcionParada":""},{"latitud":-26.8730320000000000,"longitud":-65.2230250000000000,"parada":false,"codigoParada":"","descripcionParada":""},{"latitud":-26.8730350000000000,"longitud":-65.2230320000000000,"parada":false,"codigoParada":"","descripcionParada":""},{"latitud":-26.8730420000000000,"longitud":-65.2230260000000000,"parada":false,"codigoParada":"","descripcionParada":""},{"latitud":-26.8732480000000000,"longitud":-65.2231050000000000,"parada":false,"codigoParada":"","descripcionParada":""},{"latitud":-26.8748650000000000,"longitud":-65.2238090000000000,"parada":false,"codigoParada":"","descripcionParada":""},{"latitud":-26.8757960000000000,"longitud":-65.2244210000000000,"parada":false,"codigoParada":"","descripcionParada":""},{"latitud":-26.8754340000000000,"longitud":-65.2263670000000000,"parada":false,"codigoParada":"","descripcionParada":""},{"latitud":-26.8750200000000000,"longitud":-65.2283450000000000,"parada":false,"codigoParada":"","descripcionParada":""},{"latitud":-26.8746520000000000,"longitud":-65.2303470000000000,"parada":false,"codigoParada":"","descripcionParada":""},{"latitud":-26.8742700000000000,"longitud":-65.2323280000000000,"parada":false,"codigoParada":"","descripcionParada":""},{"latitud":-26.8738840000000000,"longitud":-65.2343140000000000,"parada":false,"codigoParada":"","descripcionParada":""},{"latitud":-26.8734860000000000,"longitud":-65.2363530000000000,"parada":false,"codigoParada":"","descripcionParada":""},{"latitud":-26.8730960000000000,"longitud":-65.2383990000000000,"parada":false,"codigoParada":"","descripcionParada":""},{"latitud":-26.8726580000000000,"longitud":-65.2395480000000000,"parada":false,"codigoParada":"","descripcionParada":""},{"latitud":-26.8713360000000000,"longitud":-65.2382960000000000,"parada":false,"codigoParada":"","descripcionParada":""},{"latitud":-26.8698690000000000,"longitud":-65.2371240000000000,"parada":false,"codigoParada":"","descripcionParada":""},{"latitud":-26.8695200000000000,"longitud":-65.2369820000000000,"parada":false,"codigoParada":"","descripcionParada":""},{"latitud":-26.8694940000000000,"longitud":-65.2370460000000000,"parada":false,"codigoParada":"","descripcionParada":""},{"latitud":-26.8691330000000000,"longitud":-65.2390320000000000,"parada":false,"codigoParada":"","descripcionParada":""},{"latitud":-26.8687370000000000,"longitud":-65.2410310000000000,"parada":false,"codigoParada":"","descripcionParada":""},{"latitud":-26.8684220000000000,"longitud":-65.2426000000000000,"parada":false,"codigoParada":"","descripcionParada":""},{"latitud":-26.8680290000000000,"longitud":-65.2445900000000000,"parada":false,"codigoParada":"","descripcionParada":""},{"latitud":-26.8676760000000000,"longitud":-65.2465840000000000,"parada":false,"codigoParada":"","descripcionParada":""},{"latitud":-26.8672800000000000,"longitud":-65.2485900000000000,"parada":false,"codigoParada":"","descripcionParada":""},{"latitud":-26.8668980000000000,"longitud":-65.2505890000000000,"parada":false,"codigoParada":"","descripcionParada":""},{"latitud":-26.8665030000000000,"longitud":-65.2526170000000000,"parada":false,"codigoParada":"","descripcionParada":""},{"latitud":-26.8661320000000000,"longitud":-65.2543930000000000,"parada":false,"codigoParada":"","descripcionParada":""},{"latitud":-26.8660000000000000,"longitud":-65.2544020000000000,"parada":false,"codigoParada":"","descripcionParada":""},{"latitud":-26.8642100000000000,"longitud":-65.2539720000000000,"parada":false,"codigoParada":"","descripcionParada":""},{"latitud":-26.8636220000000000,"longitud":-65.2536350000000000,"parada":false,"codigoParada":"","descripcionParada":""},{"latitud":-26.8639830000000000,"longitud":-65.2517000000000000,"parada":false,"codigoParada":"","descripcionParada":""},{"latitud":-26.8643590000000000,"longitud":-65.2497190000000000,"parada":false,"codigoParada":"","descripcionParada":""},{"latitud":-26.8647220000000000,"longitud":-65.2476940000000000,"parada":false,"codigoParada":"","descripcionParada":""},{"latitud":-26.8650860000000000,"longitud":-65.2456390000000000,"parada":false,"codigoParada":"","descripcionParada":""},{"latitud":-26.8654530000000000,"longitud":-65.2436070000000000,"parada":false,"codigoParada":"","descripcionParada":""},{"latitud":-26.8654760000000000,"longitud":-65.2428610000000000,"parada":false,"codigoParada":"","descripcionParada":""},{"latitud":-26.8653370000000000,"longitud":-65.2428030000000000,"parada":false,"codigoParada":"","descripcionParada":""},{"latitud":-26.8635850000000000,"longitud":-65.2423350000000000,"parada":false,"codigoParada":"","descripcionParada":""},{"latitud":-26.8627270000000000,"longitud":-65.2419310000000000,"parada":false,"codigoParada":"","descripcionParada":""},{"latitud":-26.8631510000000000,"longitud":-65.2404990000000000,"parada":false,"codigoParada":"","descripcionParada":""},{"latitud":-26.8642550000000000,"longitud":-65.2405110000000000,"parada":false,"codigoParada":"","descripcionParada":""},{"latitud":-26.8646230000000000,"longitud":-65.2385790000000000,"parada":false,"codigoParada":"","descripcionParada":""},{"latitud":-26.8649810000000000,"longitud":-65.2365750000000000,"parada":false,"codigoParada":"","descripcionParada":""},{"latitud":-26.8656250000000000,"longitud":-65.2347170000000000,"parada":false,"codigoParada":"","descripcionParada":""},{"latitud":-26.8659670000000000,"longitud":-65.2344830000000000,"parada":false,"codigoParada":"","descripcionParada":""},{"latitud":-26.8675170000000000,"longitud":-65.2355560000000000,"parada":false,"codigoParada":"","descripcionParada":""},{"latitud":-26.8704960000000000,"longitud":-65.2376940000000000,"parada":false,"codigoParada":"","descripcionParada":""},{"latitud":-26.8719170000000000,"longitud":-65.2389360000000000,"parada":false,"codigoParada":"","descripcionParada":""},{"latitud":-26.8728770000000000,"longitud":-65.2395880000000000,"parada":false,"codigoParada":"","descripcionParada":""},{"latitud":-26.8732490000000000,"longitud":-65.2376550000000000,"parada":false,"codigoParada":"","descripcionParada":""},{"latitud":-26.8736470000000000,"longitud":-65.2356450000000000,"parada":false,"codigoParada":"","descripcionParada":""},{"latitud":-26.8740620000000000,"longitud":-65.2336410000000000,"parada":false,"codigoParada":"","descripcionParada":""},{"latitud":-26.8744510000000000,"longitud":-65.2316410000000000,"parada":false,"codigoParada":"","descripcionParada":""},{"latitud":-26.8748120000000000,"longitud":-65.2296240000000000,"parada":false,"codigoParada":"","descripcionParada":""},{"latitud":-26.8752240000000000,"longitud":-65.2276490000000000,"parada":false,"codigoParada":"","descripcionParada":""},{"latitud":-26.8756110000000000,"longitud":-65.2256420000000000,"parada":false,"codigoParada":"","descripcionParada":""},{"latitud":-26.8758530000000000,"longitud":-65.2244300000000000,"parada":false,"codigoParada":"","descripcionParada":""},{"latitud":-26.8758450000000000,"longitud":-65.2242310000000000,"parada":false,"codigoParada":"","descripcionParada":""},{"latitud":-26.8757240000000000,"longitud":-65.2241470000000000,"parada":false,"codigoParada":"","descripcionParada":""},{"latitud":-26.8740520000000000,"longitud":-65.2234250000000000,"parada":false,"codigoParada":"","descripcionParada":""},{"latitud":-26.8723770000000000,"longitud":-65.2226610000000000,"parada":false,"codigoParada":"","descripcionParada":""},{"latitud":-26.8706800000000000,"longitud":-65.2219220000000000,"parada":false,"codigoParada":"","descripcionParada":""},{"latitud":-26.8704360000000000,"longitud":-65.2218410000000000,"parada":false,"codigoParada":"","descripcionParada":""},{"latitud":-26.8686570000000000,"longitud":-65.2214980000000000,"parada":false,"codigoParada":"","descripcionParada":""},{"latitud":-26.8668330000000000,"longitud":-65.2211550000000000,"parada":false,"codigoParada":"","descripcionParada":""}]}